[
  {
    "key": "src/ERB/SYS_ABL/ABLUP070.ERB_L11",
    "original": "[0] - %PALAMNAME:11%の珠×{COST70(0)}、%EXPNAME:70%{COST70(1)}以上……",
    "context": "文件名: src/ERB/SYS_ABL/ABLUP070.ERB\n代码: https://github.com/EraTranz/tohoYMAEM/blob/origin/src/ERB/SYS_ABL/ABLUP070.ERB#L11"
  },
  {
    "key": "src/ERB/SYS_ABL/ABLUP070.ERB_L14",
    "original": "[100] - やめる",
    "context": "文件名: src/ERB/SYS_ABL/ABLUP070.ERB\n代码: https://github.com/EraTranz/tohoYMAEM/blob/origin/src/ERB/SYS_ABL/ABLUP070.ERB#L14"
  },
  {
    "key": "src/ERB/SYS_ABL/ABLUP070.ERB_L32",
    "original": "%ABLNAME:70%のレベルが{ABL:料理技能}になりました。",
    "context": "文件名: src/ERB/SYS_ABL/ABLUP070.ERB\n代码: https://github.com/EraTranz/tohoYMAEM/blob/origin/src/ERB/SYS_ABL/ABLUP070.ERB#L32"
  }
]