[
  {
    "key": "src/ERB/MESSAGE/2000+ 98東方,西方,黄昏/008 夢美/調教終了/K2008_END_通常5.ERB_L16",
    "original": "「ごめんなさい……　ちょっと、起き上がる力も出ないの」",
    "context": "文件名: src/ERB/MESSAGE/2000+ 98東方,西方,黄昏/008 夢美/調教終了/K2008_END_通常5.ERB\n代码: https://github.com/EraTranz/tohoYMAEM/blob/origin/src/ERB/MESSAGE/2000+%2098%E6%9D%B1%E6%96%B9,%E8%A5%BF%E6%96%B9,%E9%BB%84%E6%98%8F/008%20%E5%A4%A2%E7%BE%8E/%E8%AA%BF%E6%95%99%E7%B5%82%E4%BA%86/K2008_END_%E9%80%9A%E5%B8%B85.ERB#L16"
  },
  {
    "key": "src/ERB/MESSAGE/2000+ 98東方,西方,黄昏/008 夢美/調教終了/K2008_END_通常5.ERB_L17",
    "original": "「少しだけ休ませて、ね？」",
    "context": "文件名: src/ERB/MESSAGE/2000+ 98東方,西方,黄昏/008 夢美/調教終了/K2008_END_通常5.ERB\n代码: https://github.com/EraTranz/tohoYMAEM/blob/origin/src/ERB/MESSAGE/2000+%2098%E6%9D%B1%E6%96%B9,%E8%A5%BF%E6%96%B9,%E9%BB%84%E6%98%8F/008%20%E5%A4%A2%E7%BE%8E/%E8%AA%BF%E6%95%99%E7%B5%82%E4%BA%86/K2008_END_%E9%80%9A%E5%B8%B85.ERB#L17"
  },
  {
    "key": "src/ERB/MESSAGE/2000+ 98東方,西方,黄昏/008 夢美/調教終了/K2008_END_通常5.ERB_L19",
    "original": "「え、もう帰っちゃうの？」",
    "context": "文件名: src/ERB/MESSAGE/2000+ 98東方,西方,黄昏/008 夢美/調教終了/K2008_END_通常5.ERB\n代码: https://github.com/EraTranz/tohoYMAEM/blob/origin/src/ERB/MESSAGE/2000+%2098%E6%9D%B1%E6%96%B9,%E8%A5%BF%E6%96%B9,%E9%BB%84%E6%98%8F/008%20%E5%A4%A2%E7%BE%8E/%E8%AA%BF%E6%95%99%E7%B5%82%E4%BA%86/K2008_END_%E9%80%9A%E5%B8%B85.ERB#L19"
  },
  {
    "key": "src/ERB/MESSAGE/2000+ 98東方,西方,黄昏/008 夢美/調教終了/K2008_END_通常5.ERB_L20",
    "original": "「――今日は来てくれただけで我慢してあげる」",
    "context": "文件名: src/ERB/MESSAGE/2000+ 98東方,西方,黄昏/008 夢美/調教終了/K2008_END_通常5.ERB\n代码: https://github.com/EraTranz/tohoYMAEM/blob/origin/src/ERB/MESSAGE/2000+%2098%E6%9D%B1%E6%96%B9,%E8%A5%BF%E6%96%B9,%E9%BB%84%E6%98%8F/008%20%E5%A4%A2%E7%BE%8E/%E8%AA%BF%E6%95%99%E7%B5%82%E4%BA%86/K2008_END_%E9%80%9A%E5%B8%B85.ERB#L20"
  },
  {
    "key": "src/ERB/MESSAGE/2000+ 98東方,西方,黄昏/008 夢美/調教終了/K2008_END_通常5.ERB_L21",
    "original": "「だから次は……　期待していいのよね？」",
    "context": "文件名: src/ERB/MESSAGE/2000+ 98東方,西方,黄昏/008 夢美/調教終了/K2008_END_通常5.ERB\n代码: https://github.com/EraTranz/tohoYMAEM/blob/origin/src/ERB/MESSAGE/2000+%2098%E6%9D%B1%E6%96%B9,%E8%A5%BF%E6%96%B9,%E9%BB%84%E6%98%8F/008%20%E5%A4%A2%E7%BE%8E/%E8%AA%BF%E6%95%99%E7%B5%82%E4%BA%86/K2008_END_%E9%80%9A%E5%B8%B85.ERB#L21"
  },
  {
    "key": "src/ERB/MESSAGE/2000+ 98東方,西方,黄昏/008 夢美/調教終了/K2008_END_通常5.ERB_L32",
    "original": "「もう終わりなのね。　楽しい時間ってすぐ過ぎちゃうわ」",
    "context": "文件名: src/ERB/MESSAGE/2000+ 98東方,西方,黄昏/008 夢美/調教終了/K2008_END_通常5.ERB\n代码: https://github.com/EraTranz/tohoYMAEM/blob/origin/src/ERB/MESSAGE/2000+%2098%E6%9D%B1%E6%96%B9,%E8%A5%BF%E6%96%B9,%E9%BB%84%E6%98%8F/008%20%E5%A4%A2%E7%BE%8E/%E8%AA%BF%E6%95%99%E7%B5%82%E4%BA%86/K2008_END_%E9%80%9A%E5%B8%B85.ERB#L32"
  },
  {
    "key": "src/ERB/MESSAGE/2000+ 98東方,西方,黄昏/008 夢美/調教終了/K2008_END_通常5.ERB_L33",
    "original": "「ねえ、次はいつ来てくれるの？」",
    "context": "文件名: src/ERB/MESSAGE/2000+ 98東方,西方,黄昏/008 夢美/調教終了/K2008_END_通常5.ERB\n代码: https://github.com/EraTranz/tohoYMAEM/blob/origin/src/ERB/MESSAGE/2000+%2098%E6%9D%B1%E6%96%B9,%E8%A5%BF%E6%96%B9,%E9%BB%84%E6%98%8F/008%20%E5%A4%A2%E7%BE%8E/%E8%AA%BF%E6%95%99%E7%B5%82%E4%BA%86/K2008_END_%E9%80%9A%E5%B8%B85.ERB#L33"
  },
  {
    "key": "src/ERB/MESSAGE/2000+ 98東方,西方,黄昏/008 夢美/調教終了/K2008_END_通常5.ERB_L34",
    "original": "「お早いご来訪、お待ちしてるわ♪」",
    "context": "文件名: src/ERB/MESSAGE/2000+ 98東方,西方,黄昏/008 夢美/調教終了/K2008_END_通常5.ERB\n代码: https://github.com/EraTranz/tohoYMAEM/blob/origin/src/ERB/MESSAGE/2000+%2098%E6%9D%B1%E6%96%B9,%E8%A5%BF%E6%96%B9,%E9%BB%84%E6%98%8F/008%20%E5%A4%A2%E7%BE%8E/%E8%AA%BF%E6%95%99%E7%B5%82%E4%BA%86/K2008_END_%E9%80%9A%E5%B8%B85.ERB#L34"
  },
  {
    "key": "src/ERB/MESSAGE/2000+ 98東方,西方,黄昏/008 夢美/調教終了/K2008_END_通常5.ERB_L45",
    "original": "「お、終わる前に、おちんちんイかせてください」",
    "context": "文件名: src/ERB/MESSAGE/2000+ 98東方,西方,黄昏/008 夢美/調教終了/K2008_END_通常5.ERB\n代码: https://github.com/EraTranz/tohoYMAEM/blob/origin/src/ERB/MESSAGE/2000+%2098%E6%9D%B1%E6%96%B9,%E8%A5%BF%E6%96%B9,%E9%BB%84%E6%98%8F/008%20%E5%A4%A2%E7%BE%8E/%E8%AA%BF%E6%95%99%E7%B5%82%E4%BA%86/K2008_END_%E9%80%9A%E5%B8%B85.ERB#L45"
  },
  {
    "key": "src/ERB/MESSAGE/2000+ 98東方,西方,黄昏/008 夢美/調教終了/K2008_END_通常5.ERB_L47",
    "original": "「クリちゃん、最後に弄らせてください」",
    "context": "文件名: src/ERB/MESSAGE/2000+ 98東方,西方,黄昏/008 夢美/調教終了/K2008_END_通常5.ERB\n代码: https://github.com/EraTranz/tohoYMAEM/blob/origin/src/ERB/MESSAGE/2000+%2098%E6%9D%B1%E6%96%B9,%E8%A5%BF%E6%96%B9,%E9%BB%84%E6%98%8F/008%20%E5%A4%A2%E7%BE%8E/%E8%AA%BF%E6%95%99%E7%B5%82%E4%BA%86/K2008_END_%E9%80%9A%E5%B8%B85.ERB#L47"
  },
  {
    "key": "src/ERB/MESSAGE/2000+ 98東方,西方,黄昏/008 夢美/調教終了/K2008_END_通常5.ERB_L49",
    "original": "「お股がムズムズして落ち着かないの」",
    "context": "文件名: src/ERB/MESSAGE/2000+ 98東方,西方,黄昏/008 夢美/調教終了/K2008_END_通常5.ERB\n代码: https://github.com/EraTranz/tohoYMAEM/blob/origin/src/ERB/MESSAGE/2000+%2098%E6%9D%B1%E6%96%B9,%E8%A5%BF%E6%96%B9,%E9%BB%84%E6%98%8F/008%20%E5%A4%A2%E7%BE%8E/%E8%AA%BF%E6%95%99%E7%B5%82%E4%BA%86/K2008_END_%E9%80%9A%E5%B8%B85.ERB#L49"
  },
  {
    "key": "src/ERB/MESSAGE/2000+ 98東方,西方,黄昏/008 夢美/調教終了/K2008_END_通常5.ERB_L59",
    "original": "「あ……　お、終わりなの？」",
    "context": "文件名: src/ERB/MESSAGE/2000+ 98東方,西方,黄昏/008 夢美/調教終了/K2008_END_通常5.ERB\n代码: https://github.com/EraTranz/tohoYMAEM/blob/origin/src/ERB/MESSAGE/2000+%2098%E6%9D%B1%E6%96%B9,%E8%A5%BF%E6%96%B9,%E9%BB%84%E6%98%8F/008%20%E5%A4%A2%E7%BE%8E/%E8%AA%BF%E6%95%99%E7%B5%82%E4%BA%86/K2008_END_%E9%80%9A%E5%B8%B85.ERB#L59"
  },
  {
    "key": "src/ERB/MESSAGE/2000+ 98東方,西方,黄昏/008 夢美/調教終了/K2008_END_通常5.ERB_L60",
    "original": "「最後に、おまんこイかせてください……　子宮が疼いちゃってるの」",
    "context": "文件名: src/ERB/MESSAGE/2000+ 98東方,西方,黄昏/008 夢美/調教終了/K2008_END_通常5.ERB\n代码: https://github.com/EraTranz/tohoYMAEM/blob/origin/src/ERB/MESSAGE/2000+%2098%E6%9D%B1%E6%96%B9,%E8%A5%BF%E6%96%B9,%E9%BB%84%E6%98%8F/008%20%E5%A4%A2%E7%BE%8E/%E8%AA%BF%E6%95%99%E7%B5%82%E4%BA%86/K2008_END_%E9%80%9A%E5%B8%B85.ERB#L60"
  },
  {
    "key": "src/ERB/MESSAGE/2000+ 98東方,西方,黄昏/008 夢美/調教終了/K2008_END_通常5.ERB_L70",
    "original": "「あのね、終わる前にちょっとだけ、お願いがあるの」",
    "context": "文件名: src/ERB/MESSAGE/2000+ 98東方,西方,黄昏/008 夢美/調教終了/K2008_END_通常5.ERB\n代码: https://github.com/EraTranz/tohoYMAEM/blob/origin/src/ERB/MESSAGE/2000+%2098%E6%9D%B1%E6%96%B9,%E8%A5%BF%E6%96%B9,%E9%BB%84%E6%98%8F/008%20%E5%A4%A2%E7%BE%8E/%E8%AA%BF%E6%95%99%E7%B5%82%E4%BA%86/K2008_END_%E9%80%9A%E5%B8%B85.ERB#L70"
  },
  {
    "key": "src/ERB/MESSAGE/2000+ 98東方,西方,黄昏/008 夢美/調教終了/K2008_END_通常5.ERB_L71",
    "original": "「お尻の穴、弄って欲しいんだけど……　だめ？」",
    "context": "文件名: src/ERB/MESSAGE/2000+ 98東方,西方,黄昏/008 夢美/調教終了/K2008_END_通常5.ERB\n代码: https://github.com/EraTranz/tohoYMAEM/blob/origin/src/ERB/MESSAGE/2000+%2098%E6%9D%B1%E6%96%B9,%E8%A5%BF%E6%96%B9,%E9%BB%84%E6%98%8F/008%20%E5%A4%A2%E7%BE%8E/%E8%AA%BF%E6%95%99%E7%B5%82%E4%BA%86/K2008_END_%E9%80%9A%E5%B8%B85.ERB#L71"
  },
  {
    "key": "src/ERB/MESSAGE/2000+ 98東方,西方,黄昏/008 夢美/調教終了/K2008_END_通常5.ERB_L72",
    "original": "「ちょっと、ちょっとだけでいいから！　むず痒いのスッキリさせて！！」",
    "context": "文件名: src/ERB/MESSAGE/2000+ 98東方,西方,黄昏/008 夢美/調教終了/K2008_END_通常5.ERB\n代码: https://github.com/EraTranz/tohoYMAEM/blob/origin/src/ERB/MESSAGE/2000+%2098%E6%9D%B1%E6%96%B9,%E8%A5%BF%E6%96%B9,%E9%BB%84%E6%98%8F/008%20%E5%A4%A2%E7%BE%8E/%E8%AA%BF%E6%95%99%E7%B5%82%E4%BA%86/K2008_END_%E9%80%9A%E5%B8%B85.ERB#L72"
  },
  {
    "key": "src/ERB/MESSAGE/2000+ 98東方,西方,黄昏/008 夢美/調教終了/K2008_END_通常5.ERB_L82",
    "original": "「……ねえ、終わる前に一つお願い聞いてくれる？」",
    "context": "文件名: src/ERB/MESSAGE/2000+ 98東方,西方,黄昏/008 夢美/調教終了/K2008_END_通常5.ERB\n代码: https://github.com/EraTranz/tohoYMAEM/blob/origin/src/ERB/MESSAGE/2000+%2098%E6%9D%B1%E6%96%B9,%E8%A5%BF%E6%96%B9,%E9%BB%84%E6%98%8F/008%20%E5%A4%A2%E7%BE%8E/%E8%AA%BF%E6%95%99%E7%B5%82%E4%BA%86/K2008_END_%E9%80%9A%E5%B8%B85.ERB#L82"
  },
  {
    "key": "src/ERB/MESSAGE/2000+ 98東方,西方,黄昏/008 夢美/調教終了/K2008_END_通常5.ERB_L83",
    "original": "「胸がピクピクってなって、ドキドキして、苦しいの」",
    "context": "文件名: src/ERB/MESSAGE/2000+ 98東方,西方,黄昏/008 夢美/調教終了/K2008_END_通常5.ERB\n代码: https://github.com/EraTranz/tohoYMAEM/blob/origin/src/ERB/MESSAGE/2000+%2098%E6%9D%B1%E6%96%B9,%E8%A5%BF%E6%96%B9,%E9%BB%84%E6%98%8F/008%20%E5%A4%A2%E7%BE%8E/%E8%AA%BF%E6%95%99%E7%B5%82%E4%BA%86/K2008_END_%E9%80%9A%E5%B8%B85.ERB#L83"
  },
  {
    "key": "src/ERB/MESSAGE/2000+ 98東方,西方,黄昏/008 夢美/調教終了/K2008_END_通常5.ERB_L84",
    "original": "「優しくマッサージして……　くれるわよね」",
    "context": "文件名: src/ERB/MESSAGE/2000+ 98東方,西方,黄昏/008 夢美/調教終了/K2008_END_通常5.ERB\n代码: https://github.com/EraTranz/tohoYMAEM/blob/origin/src/ERB/MESSAGE/2000+%2098%E6%9D%B1%E6%96%B9,%E8%A5%BF%E6%96%B9,%E9%BB%84%E6%98%8F/008%20%E5%A4%A2%E7%BE%8E/%E8%AA%BF%E6%95%99%E7%B5%82%E4%BA%86/K2008_END_%E9%80%9A%E5%B8%B85.ERB#L84"
  },
  {
    "key": "src/ERB/MESSAGE/2000+ 98東方,西方,黄昏/008 夢美/調教終了/K2008_END_通常5.ERB_L93",
    "original": "「おちんぽ、パンパンに膨らんでるのに終わりなんて」",
    "context": "文件名: src/ERB/MESSAGE/2000+ 98東方,西方,黄昏/008 夢美/調教終了/K2008_END_通常5.ERB\n代码: https://github.com/EraTranz/tohoYMAEM/blob/origin/src/ERB/MESSAGE/2000+%2098%E6%9D%B1%E6%96%B9,%E8%A5%BF%E6%96%B9,%E9%BB%84%E6%98%8F/008%20%E5%A4%A2%E7%BE%8E/%E8%AA%BF%E6%95%99%E7%B5%82%E4%BA%86/K2008_END_%E9%80%9A%E5%B8%B85.ERB#L93"
  },
  {
    "key": "src/ERB/MESSAGE/2000+ 98東方,西方,黄昏/008 夢美/調教終了/K2008_END_通常5.ERB_L94",
    "original": "「ねえ、射精させてよ。　いいでしょ？　ほらほら」",
    "context": "文件名: src/ERB/MESSAGE/2000+ 98東方,西方,黄昏/008 夢美/調教終了/K2008_END_通常5.ERB\n代码: https://github.com/EraTranz/tohoYMAEM/blob/origin/src/ERB/MESSAGE/2000+%2098%E6%9D%B1%E6%96%B9,%E8%A5%BF%E6%96%B9,%E9%BB%84%E6%98%8F/008%20%E5%A4%A2%E7%BE%8E/%E8%AA%BF%E6%95%99%E7%B5%82%E4%BA%86/K2008_END_%E9%80%9A%E5%B8%B85.ERB#L94"
  },
  {
    "key": "src/ERB/MESSAGE/2000+ 98東方,西方,黄昏/008 夢美/調教終了/K2008_END_通常5.ERB_L103",
    "original": "「おっぱいも乳首もパンパンに膨らんでる……」",
    "context": "文件名: src/ERB/MESSAGE/2000+ 98東方,西方,黄昏/008 夢美/調教終了/K2008_END_通常5.ERB\n代码: https://github.com/EraTranz/tohoYMAEM/blob/origin/src/ERB/MESSAGE/2000+%2098%E6%9D%B1%E6%96%B9,%E8%A5%BF%E6%96%B9,%E9%BB%84%E6%98%8F/008%20%E5%A4%A2%E7%BE%8E/%E8%AA%BF%E6%95%99%E7%B5%82%E4%BA%86/K2008_END_%E9%80%9A%E5%B8%B85.ERB#L103"
  },
  {
    "key": "src/ERB/MESSAGE/2000+ 98東方,西方,黄昏/008 夢美/調教終了/K2008_END_通常5.ERB_L104",
    "original": "「楽しい楽しい乳搾りの延長戦とか、どう？　興味ない？」",
    "context": "文件名: src/ERB/MESSAGE/2000+ 98東方,西方,黄昏/008 夢美/調教終了/K2008_END_通常5.ERB\n代码: https://github.com/EraTranz/tohoYMAEM/blob/origin/src/ERB/MESSAGE/2000+%2098%E6%9D%B1%E6%96%B9,%E8%A5%BF%E6%96%B9,%E9%BB%84%E6%98%8F/008%20%E5%A4%A2%E7%BE%8E/%E8%AA%BF%E6%95%99%E7%B5%82%E4%BA%86/K2008_END_%E9%80%9A%E5%B8%B85.ERB#L104"
  },
  {
    "key": "src/ERB/MESSAGE/2000+ 98東方,西方,黄昏/008 夢美/調教終了/K2008_END_通常5.ERB_L113",
    "original": "「ねね、ちょっとトイレまで付き合ってくれない？」",
    "context": "文件名: src/ERB/MESSAGE/2000+ 98東方,西方,黄昏/008 夢美/調教終了/K2008_END_通常5.ERB\n代码: https://github.com/EraTranz/tohoYMAEM/blob/origin/src/ERB/MESSAGE/2000+%2098%E6%9D%B1%E6%96%B9,%E8%A5%BF%E6%96%B9,%E9%BB%84%E6%98%8F/008%20%E5%A4%A2%E7%BE%8E/%E8%AA%BF%E6%95%99%E7%B5%82%E4%BA%86/K2008_END_%E9%80%9A%E5%B8%B85.ERB#L113"
  },
  {
    "key": "src/ERB/MESSAGE/2000+ 98東方,西方,黄昏/008 夢美/調教終了/K2008_END_通常5.ERB_L114",
    "original": "「いいじゃない、一息つくときの連れションって、やってみたいの」",
    "context": "文件名: src/ERB/MESSAGE/2000+ 98東方,西方,黄昏/008 夢美/調教終了/K2008_END_通常5.ERB\n代码: https://github.com/EraTranz/tohoYMAEM/blob/origin/src/ERB/MESSAGE/2000+%2098%E6%9D%B1%E6%96%B9,%E8%A5%BF%E6%96%B9,%E9%BB%84%E6%98%8F/008%20%E5%A4%A2%E7%BE%8E/%E8%AA%BF%E6%95%99%E7%B5%82%E4%BA%86/K2008_END_%E9%80%9A%E5%B8%B85.ERB#L114"
  },
  {
    "key": "src/ERB/MESSAGE/2000+ 98東方,西方,黄昏/008 夢美/調教終了/K2008_END_通常5.ERB_L123",
    "original": "「えへへぇ♪　ねえ、次は何するの？」",
    "context": "文件名: src/ERB/MESSAGE/2000+ 98東方,西方,黄昏/008 夢美/調教終了/K2008_END_通常5.ERB\n代码: https://github.com/EraTranz/tohoYMAEM/blob/origin/src/ERB/MESSAGE/2000+%2098%E6%9D%B1%E6%96%B9,%E8%A5%BF%E6%96%B9,%E9%BB%84%E6%98%8F/008%20%E5%A4%A2%E7%BE%8E/%E8%AA%BF%E6%95%99%E7%B5%82%E4%BA%86/K2008_END_%E9%80%9A%E5%B8%B85.ERB#L123"
  },
  {
    "key": "src/ERB/MESSAGE/2000+ 98東方,西方,黄昏/008 夢美/調教終了/K2008_END_通常5.ERB_L124",
    "original": "「え、これで終わり？　もうちょっと頑張りたかったわ」",
    "context": "文件名: src/ERB/MESSAGE/2000+ 98東方,西方,黄昏/008 夢美/調教終了/K2008_END_通常5.ERB\n代码: https://github.com/EraTranz/tohoYMAEM/blob/origin/src/ERB/MESSAGE/2000+%2098%E6%9D%B1%E6%96%B9,%E8%A5%BF%E6%96%B9,%E9%BB%84%E6%98%8F/008%20%E5%A4%A2%E7%BE%8E/%E8%AA%BF%E6%95%99%E7%B5%82%E4%BA%86/K2008_END_%E9%80%9A%E5%B8%B85.ERB#L124"
  },
  {
    "key": "src/ERB/MESSAGE/2000+ 98東方,西方,黄昏/008 夢美/調教終了/K2008_END_通常5.ERB_L125",
    "original": "「……火照っちゃった体、どうしてくれるのよ」",
    "context": "文件名: src/ERB/MESSAGE/2000+ 98東方,西方,黄昏/008 夢美/調教終了/K2008_END_通常5.ERB\n代码: https://github.com/EraTranz/tohoYMAEM/blob/origin/src/ERB/MESSAGE/2000+%2098%E6%9D%B1%E6%96%B9,%E8%A5%BF%E6%96%B9,%E9%BB%84%E6%98%8F/008%20%E5%A4%A2%E7%BE%8E/%E8%AA%BF%E6%95%99%E7%B5%82%E4%BA%86/K2008_END_%E9%80%9A%E5%B8%B85.ERB#L125"
  },
  {
    "key": "src/ERB/MESSAGE/2000+ 98東方,西方,黄昏/008 夢美/調教終了/K2008_END_通常5.ERB_L126",
    "original": "「次は！　私がバテちゃうまで頑張って頂戴ね」",
    "context": "文件名: src/ERB/MESSAGE/2000+ 98東方,西方,黄昏/008 夢美/調教終了/K2008_END_通常5.ERB\n代码: https://github.com/EraTranz/tohoYMAEM/blob/origin/src/ERB/MESSAGE/2000+%2098%E6%9D%B1%E6%96%B9,%E8%A5%BF%E6%96%B9,%E9%BB%84%E6%98%8F/008%20%E5%A4%A2%E7%BE%8E/%E8%AA%BF%E6%95%99%E7%B5%82%E4%BA%86/K2008_END_%E9%80%9A%E5%B8%B85.ERB#L126"
  },
  {
    "key": "src/ERB/MESSAGE/2000+ 98東方,西方,黄昏/008 夢美/調教終了/K2008_END_通常5.ERB_L138",
    "original": "「はーっ、はーっ、%K2008FS_CALL_MY_V()%に精液出しすぎぃ」",
    "context": "文件名: src/ERB/MESSAGE/2000+ 98東方,西方,黄昏/008 夢美/調教終了/K2008_END_通常5.ERB\n代码: https://github.com/EraTranz/tohoYMAEM/blob/origin/src/ERB/MESSAGE/2000+%2098%E6%9D%B1%E6%96%B9,%E8%A5%BF%E6%96%B9,%E9%BB%84%E6%98%8F/008%20%E5%A4%A2%E7%BE%8E/%E8%AA%BF%E6%95%99%E7%B5%82%E4%BA%86/K2008_END_%E9%80%9A%E5%B8%B85.ERB#L138"
  },
  {
    "key": "src/ERB/MESSAGE/2000+ 98東方,西方,黄昏/008 夢美/調教終了/K2008_END_通常5.ERB_L141",
    "original": "「ほら見える？　汚い音立てて白濁液が吹き出てるの」",
    "context": "文件名: src/ERB/MESSAGE/2000+ 98東方,西方,黄昏/008 夢美/調教終了/K2008_END_通常5.ERB\n代码: https://github.com/EraTranz/tohoYMAEM/blob/origin/src/ERB/MESSAGE/2000+%2098%E6%9D%B1%E6%96%B9,%E8%A5%BF%E6%96%B9,%E9%BB%84%E6%98%8F/008%20%E5%A4%A2%E7%BE%8E/%E8%AA%BF%E6%95%99%E7%B5%82%E4%BA%86/K2008_END_%E9%80%9A%E5%B8%B85.ERB#L141"
  },
  {
    "key": "src/ERB/MESSAGE/2000+ 98東方,西方,黄昏/008 夢美/調教終了/K2008_END_通常5.ERB_L143",
    "original": "「んぉお゛、溜まりすぎてザーメン潮吹きできてるぅ♪」",
    "context": "文件名: src/ERB/MESSAGE/2000+ 98東方,西方,黄昏/008 夢美/調教終了/K2008_END_通常5.ERB\n代码: https://github.com/EraTranz/tohoYMAEM/blob/origin/src/ERB/MESSAGE/2000+%2098%E6%9D%B1%E6%96%B9,%E8%A5%BF%E6%96%B9,%E9%BB%84%E6%98%8F/008%20%E5%A4%A2%E7%BE%8E/%E8%AA%BF%E6%95%99%E7%B5%82%E4%BA%86/K2008_END_%E9%80%9A%E5%B8%B85.ERB#L143"
  },
  {
    "key": "src/ERB/MESSAGE/2000+ 98東方,西方,黄昏/008 夢美/調教終了/K2008_END_通常5.ERB_L145",
    "original": "「ブビューって！　マンコから射精止まんないぃい！！」",
    "context": "文件名: src/ERB/MESSAGE/2000+ 98東方,西方,黄昏/008 夢美/調教終了/K2008_END_通常5.ERB\n代码: https://github.com/EraTranz/tohoYMAEM/blob/origin/src/ERB/MESSAGE/2000+%2098%E6%9D%B1%E6%96%B9,%E8%A5%BF%E6%96%B9,%E9%BB%84%E6%98%8F/008%20%E5%A4%A2%E7%BE%8E/%E8%AA%BF%E6%95%99%E7%B5%82%E4%BA%86/K2008_END_%E9%80%9A%E5%B8%B85.ERB#L145"
  },
  {
    "key": "src/ERB/MESSAGE/2000+ 98東方,西方,黄昏/008 夢美/調教終了/K2008_END_通常5.ERB_L147",
    "original": "「こんなの絶対妊娠したぁ、精子が卵子の争奪戦して暴れてる♪」",
    "context": "文件名: src/ERB/MESSAGE/2000+ 98東方,西方,黄昏/008 夢美/調教終了/K2008_END_通常5.ERB\n代码: https://github.com/EraTranz/tohoYMAEM/blob/origin/src/ERB/MESSAGE/2000+%2098%E6%9D%B1%E6%96%B9,%E8%A5%BF%E6%96%B9,%E9%BB%84%E6%98%8F/008%20%E5%A4%A2%E7%BE%8E/%E8%AA%BF%E6%95%99%E7%B5%82%E4%BA%86/K2008_END_%E9%80%9A%E5%B8%B85.ERB#L147"
  },
  {
    "key": "src/ERB/MESSAGE/2000+ 98東方,西方,黄昏/008 夢美/調教終了/K2008_END_通常5.ERB_L149",
    "original": "「こんなの避妊むりぃ、受精卵ぜったい着床してるわよぉ」",
    "context": "文件名: src/ERB/MESSAGE/2000+ 98東方,西方,黄昏/008 夢美/調教終了/K2008_END_通常5.ERB\n代码: https://github.com/EraTranz/tohoYMAEM/blob/origin/src/ERB/MESSAGE/2000+%2098%E6%9D%B1%E6%96%B9,%E8%A5%BF%E6%96%B9,%E9%BB%84%E6%98%8F/008%20%E5%A4%A2%E7%BE%8E/%E8%AA%BF%E6%95%99%E7%B5%82%E4%BA%86/K2008_END_%E9%80%9A%E5%B8%B85.ERB#L149"
  },
  {
    "key": "src/ERB/MESSAGE/2000+ 98東方,西方,黄昏/008 夢美/調教終了/K2008_END_通常5.ERB_L151",
    "original": "「赤ちゃん孕んでるのに、子宮を精液タンクにされたちゃったぁ」",
    "context": "文件名: src/ERB/MESSAGE/2000+ 98東方,西方,黄昏/008 夢美/調教終了/K2008_END_通常5.ERB\n代码: https://github.com/EraTranz/tohoYMAEM/blob/origin/src/ERB/MESSAGE/2000+%2098%E6%9D%B1%E6%96%B9,%E8%A5%BF%E6%96%B9,%E9%BB%84%E6%98%8F/008%20%E5%A4%A2%E7%BE%8E/%E8%AA%BF%E6%95%99%E7%B5%82%E4%BA%86/K2008_END_%E9%80%9A%E5%B8%B85.ERB#L151"
  },
  {
    "key": "src/ERB/MESSAGE/2000+ 98東方,西方,黄昏/008 夢美/調教終了/K2008_END_通常5.ERB_L162",
    "original": "「はーっ、はーっ、%K2008FS_CALL_MY_A()%に精液出しすぎぃ」",
    "context": "文件名: src/ERB/MESSAGE/2000+ 98東方,西方,黄昏/008 夢美/調教終了/K2008_END_通常5.ERB\n代码: https://github.com/EraTranz/tohoYMAEM/blob/origin/src/ERB/MESSAGE/2000+%2098%E6%9D%B1%E6%96%B9,%E8%A5%BF%E6%96%B9,%E9%BB%84%E6%98%8F/008%20%E5%A4%A2%E7%BE%8E/%E8%AA%BF%E6%95%99%E7%B5%82%E4%BA%86/K2008_END_%E9%80%9A%E5%B8%B85.ERB#L162"
  },
  {
    "key": "src/ERB/MESSAGE/2000+ 98東方,西方,黄昏/008 夢美/調教終了/K2008_END_通常5.ERB_L165",
    "original": "「あうぅ……　%K2008FS_CALL_MY_A()%ゆるゆるにされたから流れ出ちゃうじゃない」",
    "context": "文件名: src/ERB/MESSAGE/2000+ 98東方,西方,黄昏/008 夢美/調教終了/K2008_END_通常5.ERB\n代码: https://github.com/EraTranz/tohoYMAEM/blob/origin/src/ERB/MESSAGE/2000+%2098%E6%9D%B1%E6%96%B9,%E8%A5%BF%E6%96%B9,%E9%BB%84%E6%98%8F/008%20%E5%A4%A2%E7%BE%8E/%E8%AA%BF%E6%95%99%E7%B5%82%E4%BA%86/K2008_END_%E9%80%9A%E5%B8%B85.ERB#L165"
  },
  {
    "key": "src/ERB/MESSAGE/2000+ 98東方,西方,黄昏/008 夢美/調教終了/K2008_END_通常5.ERB_L167",
    "original": "「ん゛ぁあ゛ー！　肛門からザーメン噴射とまりゃにゃい♪」",
    "context": "文件名: src/ERB/MESSAGE/2000+ 98東方,西方,黄昏/008 夢美/調教終了/K2008_END_通常5.ERB\n代码: https://github.com/EraTranz/tohoYMAEM/blob/origin/src/ERB/MESSAGE/2000+%2098%E6%9D%B1%E6%96%B9,%E8%A5%BF%E6%96%B9,%E9%BB%84%E6%98%8F/008%20%E5%A4%A2%E7%BE%8E/%E8%AA%BF%E6%95%99%E7%B5%82%E4%BA%86/K2008_END_%E9%80%9A%E5%B8%B85.ERB#L167"
  },
  {
    "key": "src/ERB/MESSAGE/2000+ 98東方,西方,黄昏/008 夢美/調教終了/K2008_END_通常5.ERB_L169",
    "original": "「も、だめぇ！　これザーメン以外のも絶対でてるっ、腸液まみれのが漏れちゃってる！」",
    "context": "文件名: src/ERB/MESSAGE/2000+ 98東方,西方,黄昏/008 夢美/調教終了/K2008_END_通常5.ERB\n代码: https://github.com/EraTranz/tohoYMAEM/blob/origin/src/ERB/MESSAGE/2000+%2098%E6%9D%B1%E6%96%B9,%E8%A5%BF%E6%96%B9,%E9%BB%84%E6%98%8F/008%20%E5%A4%A2%E7%BE%8E/%E8%AA%BF%E6%95%99%E7%B5%82%E4%BA%86/K2008_END_%E9%80%9A%E5%B8%B85.ERB#L169"
  },
  {
    "key": "src/ERB/MESSAGE/2000+ 98東方,西方,黄昏/008 夢美/調教終了/K2008_END_通常5.ERB_L171",
    "original": "「ぁ゛あ゛～♪　ケツ穴の中身全部ぶちまけちゃったぁ♪」",
    "context": "文件名: src/ERB/MESSAGE/2000+ 98東方,西方,黄昏/008 夢美/調教終了/K2008_END_通常5.ERB\n代码: https://github.com/EraTranz/tohoYMAEM/blob/origin/src/ERB/MESSAGE/2000+%2098%E6%9D%B1%E6%96%B9,%E8%A5%BF%E6%96%B9,%E9%BB%84%E6%98%8F/008%20%E5%A4%A2%E7%BE%8E/%E8%AA%BF%E6%95%99%E7%B5%82%E4%BA%86/K2008_END_%E9%80%9A%E5%B8%B85.ERB#L171"
  },
  {
    "key": "src/ERB/MESSAGE/2000+ 98東方,西方,黄昏/008 夢美/調教終了/K2008_END_通常5.ERB_L173",
    "original": "「お%K2008FS_CALL_YOUR_C()%浣腸スゴすぎぃ。　こんなの教え込まれたら、もう一人でトイレ行けないじゃない」",
    "context": "文件名: src/ERB/MESSAGE/2000+ 98東方,西方,黄昏/008 夢美/調教終了/K2008_END_通常5.ERB\n代码: https://github.com/EraTranz/tohoYMAEM/blob/origin/src/ERB/MESSAGE/2000+%2098%E6%9D%B1%E6%96%B9,%E8%A5%BF%E6%96%B9,%E9%BB%84%E6%98%8F/008%20%E5%A4%A2%E7%BE%8E/%E8%AA%BF%E6%95%99%E7%B5%82%E4%BA%86/K2008_END_%E9%80%9A%E5%B8%B85.ERB#L173"
  },
  {
    "key": "src/ERB/MESSAGE/2000+ 98東方,西方,黄昏/008 夢美/調教終了/K2008_END_通常5.ERB_L184",
    "original": "「おしっこ穴までザーメンタンクにされちゃったぁ♪」",
    "context": "文件名: src/ERB/MESSAGE/2000+ 98東方,西方,黄昏/008 夢美/調教終了/K2008_END_通常5.ERB\n代码: https://github.com/EraTranz/tohoYMAEM/blob/origin/src/ERB/MESSAGE/2000+%2098%E6%9D%B1%E6%96%B9,%E8%A5%BF%E6%96%B9,%E9%BB%84%E6%98%8F/008%20%E5%A4%A2%E7%BE%8E/%E8%AA%BF%E6%95%99%E7%B5%82%E4%BA%86/K2008_END_%E9%80%9A%E5%B8%B85.ERB#L184"
  },
  {
    "key": "src/ERB/MESSAGE/2000+ 98東方,西方,黄昏/008 夢美/調教終了/K2008_END_通常5.ERB_L186",
    "original": "「あ゛あ゛～　白くてネバネバする小便垂れ流しでき゛も゛ち゛い゛い゛～♪」",
    "context": "文件名: src/ERB/MESSAGE/2000+ 98東方,西方,黄昏/008 夢美/調教終了/K2008_END_通常5.ERB\n代码: https://github.com/EraTranz/tohoYMAEM/blob/origin/src/ERB/MESSAGE/2000+%2098%E6%9D%B1%E6%96%B9,%E8%A5%BF%E6%96%B9,%E9%BB%84%E6%98%8F/008%20%E5%A4%A2%E7%BE%8E/%E8%AA%BF%E6%95%99%E7%B5%82%E4%BA%86/K2008_END_%E9%80%9A%E5%B8%B85.ERB#L186"
  },
  {
    "key": "src/ERB/MESSAGE/2000+ 98東方,西方,黄昏/008 夢美/調教終了/K2008_END_通常5.ERB_L188",
    "original": "「ん゛ンー！！　膀胱のザーメン全部ひり出しちゃう゛ぅ゛～」",
    "context": "文件名: src/ERB/MESSAGE/2000+ 98東方,西方,黄昏/008 夢美/調教終了/K2008_END_通常5.ERB\n代码: https://github.com/EraTranz/tohoYMAEM/blob/origin/src/ERB/MESSAGE/2000+%2098%E6%9D%B1%E6%96%B9,%E8%A5%BF%E6%96%B9,%E9%BB%84%E6%98%8F/008%20%E5%A4%A2%E7%BE%8E/%E8%AA%BF%E6%95%99%E7%B5%82%E4%BA%86/K2008_END_%E9%80%9A%E5%B8%B85.ERB#L188"
  },
  {
    "key": "src/ERB/MESSAGE/2000+ 98東方,西方,黄昏/008 夢美/調教終了/K2008_END_通常5.ERB_L190",
    "original": "「あっ！　真っ黄色のオシッコまで噴水したぁ♪」",
    "context": "文件名: src/ERB/MESSAGE/2000+ 98東方,西方,黄昏/008 夢美/調教終了/K2008_END_通常5.ERB\n代码: https://github.com/EraTranz/tohoYMAEM/blob/origin/src/ERB/MESSAGE/2000+%2098%E6%9D%B1%E6%96%B9,%E8%A5%BF%E6%96%B9,%E9%BB%84%E6%98%8F/008%20%E5%A4%A2%E7%BE%8E/%E8%AA%BF%E6%95%99%E7%B5%82%E4%BA%86/K2008_END_%E9%80%9A%E5%B8%B85.ERB#L190"
  },
  {
    "key": "src/ERB/MESSAGE/2000+ 98東方,西方,黄昏/008 夢美/調教終了/K2008_END_通常5.ERB_L199",
    "original": "「んっ、最後の……　いっぱいしちゃったけど、好きだったりする？」",
    "context": "文件名: src/ERB/MESSAGE/2000+ 98東方,西方,黄昏/008 夢美/調教終了/K2008_END_通常5.ERB\n代码: https://github.com/EraTranz/tohoYMAEM/blob/origin/src/ERB/MESSAGE/2000+%2098%E6%9D%B1%E6%96%B9,%E8%A5%BF%E6%96%B9,%E9%BB%84%E6%98%8F/008%20%E5%A4%A2%E7%BE%8E/%E8%AA%BF%E6%95%99%E7%B5%82%E4%BA%86/K2008_END_%E9%80%9A%E5%B8%B85.ERB#L199"
  },
  {
    "key": "src/ERB/MESSAGE/2000+ 98東方,西方,黄昏/008 夢美/調教終了/K2008_END_通常5.ERB_L201",
    "original": "「私も気持ちよかったから、次もいっぱいしてくれるとありがたいわ」",
    "context": "文件名: src/ERB/MESSAGE/2000+ 98東方,西方,黄昏/008 夢美/調教終了/K2008_END_通常5.ERB\n代码: https://github.com/EraTranz/tohoYMAEM/blob/origin/src/ERB/MESSAGE/2000+%2098%E6%9D%B1%E6%96%B9,%E8%A5%BF%E6%96%B9,%E9%BB%84%E6%98%8F/008%20%E5%A4%A2%E7%BE%8E/%E8%AA%BF%E6%95%99%E7%B5%82%E4%BA%86/K2008_END_%E9%80%9A%E5%B8%B85.ERB#L201"
  },
  {
    "key": "src/ERB/MESSAGE/2000+ 98東方,西方,黄昏/008 夢美/調教終了/K2008_END_通常5.ERB_L203",
    "original": "「んふふ～、じゃあ今度はもっと過激にやってあげるわ」",
    "context": "文件名: src/ERB/MESSAGE/2000+ 98東方,西方,黄昏/008 夢美/調教終了/K2008_END_通常5.ERB\n代码: https://github.com/EraTranz/tohoYMAEM/blob/origin/src/ERB/MESSAGE/2000+%2098%E6%9D%B1%E6%96%B9,%E8%A5%BF%E6%96%B9,%E9%BB%84%E6%98%8F/008%20%E5%A4%A2%E7%BE%8E/%E8%AA%BF%E6%95%99%E7%B5%82%E4%BA%86/K2008_END_%E9%80%9A%E5%B8%B85.ERB#L203"
  },
  {
    "key": "src/ERB/MESSAGE/2000+ 98東方,西方,黄昏/008 夢美/調教終了/K2008_END_通常5.ERB_L205",
    "original": "「私はちょっと苦手だけど、けど、%CALLNAME:MASTER%が好きなら頑張ってみる！」",
    "context": "文件名: src/ERB/MESSAGE/2000+ 98東方,西方,黄昏/008 夢美/調教終了/K2008_END_通常5.ERB\n代码: https://github.com/EraTranz/tohoYMAEM/blob/origin/src/ERB/MESSAGE/2000+%2098%E6%9D%B1%E6%96%B9,%E8%A5%BF%E6%96%B9,%E9%BB%84%E6%98%8F/008%20%E5%A4%A2%E7%BE%8E/%E8%AA%BF%E6%95%99%E7%B5%82%E4%BA%86/K2008_END_%E9%80%9A%E5%B8%B85.ERB#L205"
  },
  {
    "key": "src/ERB/MESSAGE/2000+ 98東方,西方,黄昏/008 夢美/調教終了/K2008_END_通常5.ERB_L207",
    "original": "「ふ～ん？　そんなに私を虐めるのが好きなんだ」",
    "context": "文件名: src/ERB/MESSAGE/2000+ 98東方,西方,黄昏/008 夢美/調教終了/K2008_END_通常5.ERB\n代码: https://github.com/EraTranz/tohoYMAEM/blob/origin/src/ERB/MESSAGE/2000+%2098%E6%9D%B1%E6%96%B9,%E8%A5%BF%E6%96%B9,%E9%BB%84%E6%98%8F/008%20%E5%A4%A2%E7%BE%8E/%E8%AA%BF%E6%95%99%E7%B5%82%E4%BA%86/K2008_END_%E9%80%9A%E5%B8%B85.ERB#L207"
  },
  {
    "key": "src/ERB/MESSAGE/2000+ 98東方,西方,黄昏/008 夢美/調教終了/K2008_END_通常5.ERB_L208",
    "original": "「ふふふ、さーて、パイプ椅子はどこにしまったかしらぁ～」",
    "context": "文件名: src/ERB/MESSAGE/2000+ 98東方,西方,黄昏/008 夢美/調教終了/K2008_END_通常5.ERB\n代码: https://github.com/EraTranz/tohoYMAEM/blob/origin/src/ERB/MESSAGE/2000+%2098%E6%9D%B1%E6%96%B9,%E8%A5%BF%E6%96%B9,%E9%BB%84%E6%98%8F/008%20%E5%A4%A2%E7%BE%8E/%E8%AA%BF%E6%95%99%E7%B5%82%E4%BA%86/K2008_END_%E9%80%9A%E5%B8%B85.ERB#L208"
  },
  {
    "key": "src/ERB/MESSAGE/2000+ 98東方,西方,黄昏/008 夢美/調教終了/K2008_END_通常5.ERB_L218",
    "original": "「焦らしたまま……　終わりなの？」",
    "context": "文件名: src/ERB/MESSAGE/2000+ 98東方,西方,黄昏/008 夢美/調教終了/K2008_END_通常5.ERB\n代码: https://github.com/EraTranz/tohoYMAEM/blob/origin/src/ERB/MESSAGE/2000+%2098%E6%9D%B1%E6%96%B9,%E8%A5%BF%E6%96%B9,%E9%BB%84%E6%98%8F/008%20%E5%A4%A2%E7%BE%8E/%E8%AA%BF%E6%95%99%E7%B5%82%E4%BA%86/K2008_END_%E9%80%9A%E5%B8%B85.ERB#L218"
  },
  {
    "key": "src/ERB/MESSAGE/2000+ 98東方,西方,黄昏/008 夢美/調教終了/K2008_END_通常5.ERB_L221",
    "original": "「――触っただけで弾けちゃいそうなのに」",
    "context": "文件名: src/ERB/MESSAGE/2000+ 98東方,西方,黄昏/008 夢美/調教終了/K2008_END_通常5.ERB\n代码: https://github.com/EraTranz/tohoYMAEM/blob/origin/src/ERB/MESSAGE/2000+%2098%E6%9D%B1%E6%96%B9,%E8%A5%BF%E6%96%B9,%E9%BB%84%E6%98%8F/008%20%E5%A4%A2%E7%BE%8E/%E8%AA%BF%E6%95%99%E7%B5%82%E4%BA%86/K2008_END_%E9%80%9A%E5%B8%B85.ERB#L221"
  },
  {
    "key": "src/ERB/MESSAGE/2000+ 98東方,西方,黄昏/008 夢美/調教終了/K2008_END_通常5.ERB_L223",
    "original": "「……ずるいんだ」",
    "context": "文件名: src/ERB/MESSAGE/2000+ 98東方,西方,黄昏/008 夢美/調教終了/K2008_END_通常5.ERB\n代码: https://github.com/EraTranz/tohoYMAEM/blob/origin/src/ERB/MESSAGE/2000+%2098%E6%9D%B1%E6%96%B9,%E8%A5%BF%E6%96%B9,%E9%BB%84%E6%98%8F/008%20%E5%A4%A2%E7%BE%8E/%E8%AA%BF%E6%95%99%E7%B5%82%E4%BA%86/K2008_END_%E9%80%9A%E5%B8%B85.ERB#L223"
  },
  {
    "key": "src/ERB/MESSAGE/2000+ 98東方,西方,黄昏/008 夢美/調教終了/K2008_END_通常5.ERB_L232",
    "original": "「んー！！　満足♪　満足♪」",
    "context": "文件名: src/ERB/MESSAGE/2000+ 98東方,西方,黄昏/008 夢美/調教終了/K2008_END_通常5.ERB\n代码: https://github.com/EraTranz/tohoYMAEM/blob/origin/src/ERB/MESSAGE/2000+%2098%E6%9D%B1%E6%96%B9,%E8%A5%BF%E6%96%B9,%E9%BB%84%E6%98%8F/008%20%E5%A4%A2%E7%BE%8E/%E8%AA%BF%E6%95%99%E7%B5%82%E4%BA%86/K2008_END_%E9%80%9A%E5%B8%B85.ERB#L232"
  },
  {
    "key": "src/ERB/MESSAGE/2000+ 98東方,西方,黄昏/008 夢美/調教終了/K2008_END_通常5.ERB_L233",
    "original": "「楽しいと時間、つい忘れちゃうわね」",
    "context": "文件名: src/ERB/MESSAGE/2000+ 98東方,西方,黄昏/008 夢美/調教終了/K2008_END_通常5.ERB\n代码: https://github.com/EraTranz/tohoYMAEM/blob/origin/src/ERB/MESSAGE/2000+%2098%E6%9D%B1%E6%96%B9,%E8%A5%BF%E6%96%B9,%E9%BB%84%E6%98%8F/008%20%E5%A4%A2%E7%BE%8E/%E8%AA%BF%E6%95%99%E7%B5%82%E4%BA%86/K2008_END_%E9%80%9A%E5%B8%B85.ERB#L233"
  },
  {
    "key": "src/ERB/MESSAGE/2000+ 98東方,西方,黄昏/008 夢美/調教終了/K2008_END_通常5.ERB_L234",
    "original": "「またよろしくね、%CALLNAME:MASTER%！！」",
    "context": "文件名: src/ERB/MESSAGE/2000+ 98東方,西方,黄昏/008 夢美/調教終了/K2008_END_通常5.ERB\n代码: https://github.com/EraTranz/tohoYMAEM/blob/origin/src/ERB/MESSAGE/2000+%2098%E6%9D%B1%E6%96%B9,%E8%A5%BF%E6%96%B9,%E9%BB%84%E6%98%8F/008%20%E5%A4%A2%E7%BE%8E/%E8%AA%BF%E6%95%99%E7%B5%82%E4%BA%86/K2008_END_%E9%80%9A%E5%B8%B85.ERB#L234"
  }
]